ai4clinic/__init__.py
ai4clinic/split4drp.py
ai4clinic/graphs/__init__.py
ai4clinic/graphs/best2worst2.py
ai4clinic/graphs/drugs2waterfall.py
ai4clinic/graphs/preds2scatter.py
ai4clinic/metrics/__init__.py
ai4clinic/metrics/corr4drug.py
ai4clinic/metrics/corr4range.py
ai4clinic/metrics/loss4drug.py
ai4clinic-0.1.2.dist-info/METADATA
ai4clinic-0.1.2.dist-info/WHEEL
ai4clinic-0.1.2.dist-info/top_level.txt
ai4clinic-0.1.2.dist-info/RECORD
