Metadata-Version: 2.4
Name: ai4clinic
Version: 0.1.2
Summary: ai4clinic: Bridging AI and Clinical Practice in Cancer Research
Home-page: https://github.com/KatynaSada/ai4clinic
Author: Katyna Sada del Real, Josefina Arcagni
Author-email: ksada@unav.es
Project-URL: Source, https://github.com/KatynaSada/ai4clinic
Project-URL: Tracker, https://github.com/KatynaSada/ai4clinic/issues
Keywords: python,first package
Classifier: Development Status :: 3 - Alpha
Classifier: Intended Audience :: Science/Research
Classifier: Programming Language :: Python :: 3
Classifier: Operating System :: MacOS
Classifier: Operating System :: Microsoft :: Windows
Classifier: Operating System :: POSIX :: Linux
Classifier: Topic :: Scientific/Engineering :: Artificial Intelligence
Classifier: Natural Language :: English
Requires-Python: >=3.9
Requires-Dist: numpy>=1.24.0
Requires-Dist: pandas>=1.5.0
Requires-Dist: matplotlib>=3.7.0
Requires-Dist: torch>=2.0.0
Requires-Dist: torchmetrics>=0.11.0
Requires-Dist: rich>=13.3.0
Dynamic: author
Dynamic: author-email
Dynamic: classifier
Dynamic: description
Dynamic: description-content-type
Dynamic: home-page
Dynamic: keywords
Dynamic: project-url
Dynamic: requires-dist
Dynamic: requires-python
Dynamic: summary
